README.md
setup.py
spk_pulumi_netbox/__init__.py
spk_pulumi_netbox/_inputs.py
spk_pulumi_netbox/_utilities.py
spk_pulumi_netbox/aggregate.py
spk_pulumi_netbox/asn.py
spk_pulumi_netbox/available_ip_address.py
spk_pulumi_netbox/available_prefix.py
spk_pulumi_netbox/cable.py
spk_pulumi_netbox/circuit.py
spk_pulumi_netbox/circuit_provider.py
spk_pulumi_netbox/circuit_termination.py
spk_pulumi_netbox/circuit_type.py
spk_pulumi_netbox/cluster.py
spk_pulumi_netbox/cluster_group.py
spk_pulumi_netbox/cluster_type.py
spk_pulumi_netbox/contact.py
spk_pulumi_netbox/contact_assignment.py
spk_pulumi_netbox/contact_group.py
spk_pulumi_netbox/contact_role.py
spk_pulumi_netbox/custom_field.py
spk_pulumi_netbox/custom_field_choice_set.py
spk_pulumi_netbox/device.py
spk_pulumi_netbox/device_console_port.py
spk_pulumi_netbox/device_console_server_port.py
spk_pulumi_netbox/device_front_port.py
spk_pulumi_netbox/device_interface.py
spk_pulumi_netbox/device_module_bay.py
spk_pulumi_netbox/device_power_outlet.py
spk_pulumi_netbox/device_power_port.py
spk_pulumi_netbox/device_primary_ip.py
spk_pulumi_netbox/device_rear_port.py
spk_pulumi_netbox/device_role.py
spk_pulumi_netbox/device_type.py
spk_pulumi_netbox/event_rule.py
spk_pulumi_netbox/get_asn.py
spk_pulumi_netbox/get_asns.py
spk_pulumi_netbox/get_available_prefix.py
spk_pulumi_netbox/get_cluster.py
spk_pulumi_netbox/get_cluster_group.py
spk_pulumi_netbox/get_cluster_type.py
spk_pulumi_netbox/get_contact.py
spk_pulumi_netbox/get_contact_group.py
spk_pulumi_netbox/get_contact_role.py
spk_pulumi_netbox/get_device_interfaces.py
spk_pulumi_netbox/get_device_role.py
spk_pulumi_netbox/get_device_type.py
spk_pulumi_netbox/get_devices.py
spk_pulumi_netbox/get_interfaces.py
spk_pulumi_netbox/get_ip_addresses.py
spk_pulumi_netbox/get_ip_range.py
spk_pulumi_netbox/get_ipam_role.py
spk_pulumi_netbox/get_location.py
spk_pulumi_netbox/get_locations.py
spk_pulumi_netbox/get_platform.py
spk_pulumi_netbox/get_prefix.py
spk_pulumi_netbox.egg-info/PKG-INFO
spk_pulumi_netbox.egg-info/SOURCES.txt
spk_pulumi_netbox.egg-info/dependency_links.txt
spk_pulumi_netbox.egg-info/not-zip-safe
spk_pulumi_netbox.egg-info/requires.txt
spk_pulumi_netbox.egg-info/top_level.txt
