Metadata-Version: 2.1
Name: spk-pulumi-netbox
Version: 0.1.5
Summary: A Pulumi package for creating and managing Netbox resources.
Home-page: https://github.com/SpikeeLabs/pulumi-netbox
License: Apache-2.0
Project-URL: Repository, https://github.com/SpikeeLabs/pulumi-netbox
Keywords: pulumi netbox category/cloud
Requires-Python: >=3.8
